summaraize/__init__.py
summaraize/__main__.py
summaraize/summarize.py
summaraize/ui/__init__.py
summaraize/ui/api_key_page.py
summaraize/ui/config.py
summaraize/ui/ffmpeg_error_page.py
summaraize/ui/markdown.py
summaraize/ui/show_summary_page.py
summaraize/ui/spinner.py
summaraize/ui/summarize_page.py
summaraize/ui/ui.py
summaraize/ui/upload_recording_page.py
summaraize-0.4.dist-info/LICENSE
summaraize-0.4.dist-info/METADATA
summaraize-0.4.dist-info/WHEEL
summaraize-0.4.dist-info/top_level.txt
summaraize-0.4.dist-info/RECORD
