Metadata-Version: 2.1
Name: summaraize
Version: 0.4
Summary: Analyze event video recordings with cloud hosted AI.
Home-page: https://github.com/juslop/summaraize
Author: Jussi Löppönen
Classifier: Programming Language :: Python :: 3
Classifier: License :: OSI Approved :: MIT License
Classifier: Operating System :: OS Independent
Requires-Python: >=3.10
License-File: LICENSE
Requires-Dist: openai
Requires-Dist: ttkbootstrap
